{
  "prefixes": {
    "feat": "Фичи",
    "fix": "Исправления багов",
    "docs": "Документация",
    "style": "Форматирование",
    "refactor": "Рефакторинг",
    "perf": "Производительность",
    "test": "Тесты",
    "chore": "Служебные изменения"
  },
  "emojis": {
    "feat": "✨",
    "fix": "🛠️",
    "docs": "📖",
    "style": "💎",
    "refactor": "♻️",
    "perf": "⚡️",
    "test": "✅",
    "chore": "🧹"
  }
}
